qcloud_vod/__init__.py
qcloud_vod/common.py
qcloud_vod/exception.py
qcloud_vod/model.py
qcloud_vod/vod_upload_client.py
vod_python_sdk-1.4.4.dist-info/LICENSE
vod_python_sdk-1.4.4.dist-info/METADATA
vod_python_sdk-1.4.4.dist-info/WHEEL
vod_python_sdk-1.4.4.dist-info/top_level.txt
vod_python_sdk-1.4.4.dist-info/RECORD
