Metadata-Version: 2.1
Name: vod-python-sdk
Version: 1.4.4
Summary: vod-python-sdk
Home-page: https://github.com/tencentyun/vod-python-sdk
Author: vod
Author-email: 1654382995@qq.com
License: MIT
Platform: UNKNOWN
Requires-Dist: cos-python-sdk-v5 (>=1.9.24)
Requires-Dist: tencentcloud-sdk-python
